LICENSE
README.md
pyproject.toml
setup.py
c_sar_denarius/__init__.py
c_sar_denarius/cli.py
c_sar_denarius/constants.py
c_sar_denarius/markdown.py
c_sar_denarius/md_utils.py
c_sar_denarius/serve.py
c_sar_denarius/utils.py
c_sar_denarius.egg-info/PKG-INFO
c_sar_denarius.egg-info/SOURCES.txt
c_sar_denarius.egg-info/dependency_links.txt
c_sar_denarius.egg-info/entry_points.txt
c_sar_denarius.egg-info/requires.txt
c_sar_denarius.egg-info/top_level.txt
c_sar_denarius/resources/other/denarius.css
c_sar_denarius/resources/other/denarius.png
c_sar_denarius/resources/structure/1.2.0.yaml
c_sar_denarius/resources/structure/1.3.1.yaml
c_sar_denarius/resources/structure/1.3.4.yaml
c_sar_denarius/resources/templates/README.md
c_sar_denarius/resources/templates/index.md.tmpl
c_sar_denarius/resources/templates/mkdocs.yml.tmpl