Metadata-Version: 2.1
Name: c-sar-denarius
Version: 1.0.1
Summary: Interface overlay for c-sar
Home-page: https://github.com/cancerit/c-sar-denarius
Author: Keiran M Raine
Author-email: cgphelp@sanger.ac.uk
License: AGPL-3.0
Platform: UNKNOWN
Requires-Python: >= 3.9
License-File: LICENSE
